sorrek_dataroom/api.py
sorrek_dataroom/init.py
sorrek_dataroom-1.0.4.dist-info/LICENSE.txt
sorrek_dataroom-1.0.4.dist-info/METADATA
sorrek_dataroom-1.0.4.dist-info/WHEEL
sorrek_dataroom-1.0.4.dist-info/top_level.txt
sorrek_dataroom-1.0.4.dist-info/RECORD
