Metadata-Version: 2.1
Name: sorrek-dataroom
Version: 1.0.4
Summary: For use with the Sorrek Dataroom product
Author-email: Ariel Lavi <ariel@sorrek.io>
Project-URL: Homepage, https://github.com/sorrek/sorrek-dataroom/sorrek-dataroom
Project-URL: Bug Tracker, https://github.com/sorrek/sorrek-dataroom/issues
Classifier: Programming Language :: Python :: 3
Classifier: License :: OSI Approved :: MIT License
Classifier: Operating System :: OS Independent
Requires-Python: >=3.7
License-File: LICENSE.txt
